{
  "status": {
    "new": false
  },
  "player_data": {
    "max_hp": 3.000000,
    "hp": 3.000000,
    "orbs": 2036,
    "position": {
      "x": 459.789825,
      "y": 107.000008
    },
    "arsenal": [
      0,
      10
    ],
    "equipped_gun": 1,
    "abilities": [

    ],
    "items": [
      {
        "id": 11,
        "quantity": 1
      },
      {
        "id": 16,
        "quantity": 1
      },
      {
        "id": 12,
        "quantity": 1
      },
      {
        "id": 8,
        "quantity": 1
      },
      {
        "id": 15,
        "quantity": 1
      }
    ],
    "stats": {
      "death_count": 6,
      "bullets_fired": 6517,
      "guns_collected": 2,
      "items_collected": 5,
      "orbs_collected": 2036,
      "blue_orbs": 3,
      "highest_indicator_amount": 375,
      "enemies_killed": 54,
      "rooms_discovered": 22,
      "seconds_played": 1282.529419,
      "time_trials": {
        "bryns_gun": 167.537613
      }
    }
  },
  "save_point_id": 115,
  "unlocked_doors": [
    11,
    15,
    8
  ],
  "opened_chests": [
    5768,
    377,
    56790,
    7880,
    338223,
    323,
    211,
    8883,
    45560,
    77122,
    9981
  ],
  "quest_progressions": [
    [
      0,
      0,
      0,
      1,
      0
    ],
    [
      88,
      1,
      1,
      1,
      0
    ],
    [
      63,
      1,
      1,
      1,
      0
    ],
    [
      1,
      110,
      2,
      1,
      0
    ],
    [
      1,
      110,
      1,
      1,
      0
    ],
    [
      5,
      110,
      1,
      1,
      0
    ],
    [
      5,
      115,
      2,
      1,
      0
    ]
  ],
  "destroyed_inspectables": [

  ],
  "tutorial": {
    "state": 4,
    "closed": true,
    "on": false,
    "jump": true,
    "shoot": true,
    "sprint": true,
    "map": true,
    "inventory": true
  },
  "discovered_rooms": [
    100,
    101,
    102,
    104,
    106,
    117,
    107,
    116,
    108,
    109,
    110,
    112,
    105,
    111,
    199,
    103,
    121,
    120,
    115,
    122,
    200,
    299
  ]
}
