{
  "meta": {
    "room_id": 111,
    "dimensions": [
      32,
      16
    ],
    "chunk_dimensions": [
      2,
      1
    ],
    "style": 0,
    "background": 4
  },
  "portals": [
    {
      "dimensions": [
        1,
        1
      ],
      "position": [
        27,
        13
      ],
      "source_id": 111,
      "destination_id": 105,
      "activate_on_contact": false
    }
  ],
  "platforms": [
    {
      "position": [
        61,
        2
      ],
      "dimensions": [
        3,
        3
      ],
      "extent": 10,
      "style": 2,
      "type": "standard_square",
      "start": 0.000000
    },
    {
      "position": [
        20,
        2
      ],
      "dimensions": [
        3,
        1
      ],
      "extent": 11,
      "style": 2,
      "type": "standard_up_down",
      "start": 0.000000
    },
    {
      "position": [
        12,
        2
      ],
      "dimensions": [
        3,
        1
      ],
      "extent": 10,
      "style": 2,
      "type": "standard_up_down",
      "start": 0.000000
    },
    {
      "position": [
        16,
        2
      ],
      "dimensions": [
        3,
        1
      ],
      "extent": 10,
      "style": 2,
      "type": "standard_up_down",
      "start": 0.500000
    }
  ]
}
